qvspy/__init__.py
qvspy/qvspy.py
QvsPy-0.0.3.dist-info/METADATA
QvsPy-0.0.3.dist-info/WHEEL
QvsPy-0.0.3.dist-info/top_level.txt
QvsPy-0.0.3.dist-info/RECORD
