Metadata-Version: 2.1
Name: QvsPy
Version: 0.0.3
Summary: Quantum virus sensing on Python
Home-page: https://github.com/SupertechLabs/cirq-superstaq
Author: QS Pirates
Author-email: vtomole2@gmail.com
License: Apache 2
Platform: UNKNOWN
Requires-Python: >=3.7.0
Requires-Dist: wheel
Requires-Dist: amazon-braket-sdk (==1.18.0)
Requires-Dist: boto3 (==1.21.30)
Requires-Dist: ibm-quantum-widgets (==1.0.3)
Requires-Dist: numpy (==1.21.5)
Requires-Dist: qiskit (==0.34.2)
Requires-Dist: qiskit-experiments
Requires-Dist: notebook
